fitlins/__about__.py
fitlins/__init__.py
fitlins/__main__.py
fitlins/_version.py
fitlins/conftest.py
fitlins/generate_dset.py
fitlins/cli/__init__.py
fitlins/cli/run.py
fitlins/data/fitlins.json
fitlins/data/full_report.tpl
fitlins/data/nipype.cfg
fitlins/data/conte69/tpl-conte69_hemi-L_space-fsLR_den-32k_inflated.surf.gii
fitlins/data/conte69/tpl-conte69_hemi-R_space-fsLR_den-32k_inflated.surf.gii
fitlins/interfaces/__init__.py
fitlins/interfaces/abstract.py
fitlins/interfaces/afni.py
fitlins/interfaces/bids.py
fitlins/interfaces/nistats.py
fitlins/interfaces/utils.py
fitlins/interfaces/visualizations.py
fitlins/tests/__init__.py
fitlins/tests/conftest.py
fitlins/tests/test_outputs.py
fitlins/utils/__init__.py
fitlins/utils/bids.py
fitlins/utils/collections.py
fitlins/utils/config.py
fitlins/utils/strings.py
fitlins/viz/__init__.py
fitlins/viz/contrasts.py
fitlins/viz/corr.py
fitlins/viz/reports.py
fitlins/workflows/__init__.py
fitlins/workflows/base.py
fitlins/workflows/tests/__init__.py
fitlins/workflows/tests/test_base.py
fitlins-0.11.0.dist-info/LICENSE
fitlins-0.11.0.dist-info/METADATA
fitlins-0.11.0.dist-info/WHEEL
fitlins-0.11.0.dist-info/entry_points.txt
fitlins-0.11.0.dist-info/top_level.txt
fitlins-0.11.0.dist-info/RECORD
