Metadata-Version: 2.1
Name: fitlins
Version: 0.11.0
Summary: Fit Linear Models to BIDS Datasets
Home-page: https://github.com/poldracklab/fitlins
Author: Christopher J. Markiewicz
Author-email: crn.poldracklab@gmail.com
License: 3-clause BSD
Classifier: Development Status :: 3 - Alpha
Classifier: Intended Audience :: Science/Research
Classifier: Topic :: Scientific/Engineering
Classifier: License :: OSI Approved :: BSD License
Classifier: Programming Language :: Python :: 3.7
Classifier: Programming Language :: Python :: 3.8
Classifier: Programming Language :: Python :: 3.9
Classifier: Programming Language :: Python :: 3.10
Requires-Python: >=3.7
License-File: LICENSE
Requires-Dist: nibabel (>=2.0)
Requires-Dist: nipype (>=1.3.2)
Requires-Dist: seaborn (>=0.10.0)
Requires-Dist: numpy (>=1.11)
Requires-Dist: nilearn (~=0.9.1)
Requires-Dist: pandas (>=0.19)
Requires-Dist: tables (>=3.2.1)
Requires-Dist: pybids (~=0.15.4)
Requires-Dist: jinja2
Provides-Extra: all
Requires-Dist: sphinx (~=4.5.0) ; extra == 'all'
Requires-Dist: sphinxcontrib-apidoc (~=0.3.0) ; extra == 'all'
Requires-Dist: sphinx-argparse (~=0.3.1) ; extra == 'all'
Requires-Dist: nbsphinx (~=0.8.8) ; extra == 'all'
Requires-Dist: texext (~=0.6.6) ; extra == 'all'
Requires-Dist: myst-parser (~=0.17.0) ; extra == 'all'
Requires-Dist: duecredit ; extra == 'all'
Requires-Dist: flake8 (>=3.7.0) ; extra == 'all'
Requires-Dist: coverage ; extra == 'all'
Requires-Dist: pytest ; extra == 'all'
Requires-Dist: pytest-cov ; extra == 'all'
Provides-Extra: docs
Requires-Dist: sphinx (~=4.5.0) ; extra == 'docs'
Requires-Dist: sphinxcontrib-apidoc (~=0.3.0) ; extra == 'docs'
Requires-Dist: sphinx-argparse (~=0.3.1) ; extra == 'docs'
Requires-Dist: nbsphinx (~=0.8.8) ; extra == 'docs'
Requires-Dist: texext (~=0.6.6) ; extra == 'docs'
Requires-Dist: myst-parser (~=0.17.0) ; extra == 'docs'
Provides-Extra: duecredit
Requires-Dist: duecredit ; extra == 'duecredit'
Provides-Extra: style
Requires-Dist: flake8 (>=3.7.0) ; extra == 'style'
Provides-Extra: test
Requires-Dist: coverage ; extra == 'test'
Requires-Dist: pytest ; extra == 'test'
Requires-Dist: pytest-cov ; extra == 'test'
Provides-Extra: workflow
Requires-Dist: coverage ; extra == 'workflow'
Requires-Dist: pytest ; extra == 'workflow'
Requires-Dist: pytest-cov ; extra == 'workflow'
